osiric/__init__.py
osiric/common.py
osiric/date_range/__init__.py
osiric/date_range/extractor.py
osiric/extractor.py
osiric/http/__init__.py
osiric/http/authentication/__init__.py
osiric/http/authentication/common.py
osiric/http/authentication/header_token.py
osiric/http/authentication/none.py
osiric/http/authentication/oauth.py
osiric/http/certificates/__init__.py
osiric/http/certificates/common.py
osiric/http/certificates/none.py
osiric/http/certificates/pem.py
osiric/http/extractor.py
osiric/http/ssl/__init__.py
osiric/http/ssl/common.py
osiric/http/ssl/default.py
osiric/rest/__init__.py
osiric/rest/extractor.py
osiric/rest/pagination/__init__.py
osiric/rest/pagination/common.py
osiric/rest/pagination/limit_offset.py
osiric/rest/pagination/next_url.py
osiric/rest/pagination/none.py
osiric/rest/pagination/page_number.py
osiric/rest/parsing/__init__.py
osiric/rest/parsing/common.py
osiric/rest/parsing/json_key.py
osiric/rest/parsing/none.py
osiric/util.py
osiric-0.2.2.dist-info/METADATA
osiric-0.2.2.dist-info/WHEEL
osiric-0.2.2.dist-info/RECORD
