Metadata-Version: 2.3
Name: osiric
Version: 0.2.2
Summary: Extracting data from any kind of source.
License: MIT
Author: Kevin Latusinski
Author-email: me@kevlatus.de
Requires-Python: >=3.11
Classifier: Programming Language :: Python :: 3
Classifier: License :: OSI Approved :: MIT License
Classifier: Operating System :: OS Independent
Requires-Dist: aiohttp (>=3.11.18,<4.0.0)
Requires-Dist: aioresponses (>=0.7.8,<0.8.0)
Requires-Dist: pydantic (>=2.11.4,<3.0.0)
